{"cameraMode":{"drawMode":0,"name":"Shaded","section":"Shading Mode"},"sceneLighting":true,"audioPlay":false,"sceneViewState":{"m_AlwaysRefresh":false,"showFog":true,"showSkybox":true,"showFlares":true,"showImageEffects":true,"showParticleSystems":true,"showVisualEffectGraphs":true,"m_FxEnabled":true},"in2DMode":false,"pivot":{"x":1.0778894424438477,"y":1.5386419296264649,"z":-2.134502649307251},"rotation":{"x":-0.001066701952368021,"y":0.9980151057243347,"z":0.017657233402132989,"w":0.060254473239183429},"size":1.3194715976715088,"orthographic":false}